{"id":"0db67387-4cc1-90ac-3dd1-e40ce95d03e6","name":"Midnight Craving on Behance","size":212878,"ext":"png","tags":[],"folders":[],"isDeleted":false,"url":"https://www.behance.net/gallery/46471433/Midnight-Craving","modificationTime":1512706819222,"width":3017,"height":1792,"palettes":[{"color":[236,199,191],"ratio":93.06949013157895},{"color":[24,26,37],"ratio":4.147203947368421},{"color":[240,223,74],"ratio":1.584292763157895},{"color":[213,186,112],"ratio":1.1875},{"color":[187,58,59],"ratio":0.011513157894736841}]}