{"id":"8784a14f-a8aa-72a2-5dab-15f99904da18","name":"Nếu vơ bừa một người nào đó để kết hôn, sau đó hối hận, chẳng thà chờ","size":65032,"ext":"jpg","tags":[],"folders":[],"isDeleted":false,"url":"https://www.pinterest.com/pin/402368547951754106/","modificationTime":1514966427960,"width":422,"height":750,"palettes":[{"color":[199,213,219],"ratio":59.166666666666664},{"color":[45,79,62],"ratio":18.9296875},{"color":[109,158,176],"ratio":17.16449652777778},{"color":[117,70,68],"ratio":2.14453125},{"color":[93,133,87],"ratio":2.5946180555555554}]}