{"id":"80464517-bdd3-1ed3-54ec-3b3c6ad986fb","name":"FAIRY LEYA Vkontakte stickers set – 2014 on Behance","size":446190,"ext":"png","tags":[],"folders":[],"isDeleted":false,"url":"https://www.behance.net/gallery/60650939/FAIRY-LEYA-Vkontakte-stickers-set-2014","modificationTime":1515640512703,"width":1400,"height":850,"palettes":[{"color":[235,237,241],"ratio":79.68588917525773},{"color":[224,94,116],"ratio":13.54381443298969},{"color":[188,208,48],"ratio":5.174774484536082},{"color":[78,157,215],"ratio":1.4110824742268042},{"color":[147,183,202],"ratio":0.1844394329896907}]}