{"id":"97fe74f0-6630-40d5-ddbb-30ea1a079db3","name":"Space Girl","size":311153,"ext":"jpg","tags":[],"folders":["685ee6c4-ffd4-b19d-330e-5ad2ee3b6865"],"isDeleted":false,"url":"https://dribbble.com/shots/4150287-Space-Girl","annotation":"","modificationTime":1517279899369,"width":800,"height":600,"palettes":[{"color":[228,218,228],"ratio":56.065755208333336},{"color":[47,8,172],"ratio":39.2080078125},{"color":[130,30,230],"ratio":4.053385416666667},{"color":[229,162,40],"ratio":0.6725260416666666},{"color":[100,100,228],"ratio":0.00032552083333333337}]}