{"id":"9f8d6624-5047-1427-af67-4ebda90c5bc5","name":"「ヴィネット」の画像検索结果","size":59788,"ext":"jpg","tags":[],"folders":[],"isDeleted":false,"url":"https://www.pinterest.com/pin/AaQWNf1VsGEoPPzB10shuqoV0dNVcTzBeGFgjnFSf76yBUGm2mEKadE/","modificationTime":1514965313745,"width":564,"height":595,"palettes":[{"color":[30,56,53],"ratio":81.24977650634722},{"color":[209,219,202],"ratio":9.56403838130997},{"color":[83,181,162],"ratio":6.712855354907921},{"color":[60,140,162],"ratio":0.8814589665653495},{"color":[117,116,92],"ratio":1.5918707908695393}]}