{"id":"0ad1e31d-1039-49ee-40e2-f41f3ea514c7","name":"WebUi 界面合集 on Behance","size":3322122,"ext":"png","tags":[],"folders":[],"isDeleted":false,"url":"https://www.behance.net/gallery/56692783/WebUi-","modificationTime":1516252628902,"width":1920,"height":7000,"palettes":[{"color":[245,244,243],"ratio":92.14443581225889},{"color":[64,88,61],"ratio":3.1550712601800255},{"color":[156,158,146],"ratio":3.3483578011144446},{"color":[174,160,90],"ratio":1.1664166309472783},{"color":[158,97,69],"ratio":0.18571849549935707}]}