{"id":"8dcf1da8-f7ff-6207-c64c-7b1ad84a88c0","name":"乔安娜·马林尼（Joanna Malinis）的每日彩色积木，通过Behance","size":73461,"ext":"jpg","tags":[],"folders":[],"isDeleted":false,"url":"https://www.pinterest.com/pin/85005511689823577/","modificationTime":1511839792865,"width":564,"height":1128,"processingPalette":true,"palettes":[{"color":[248,243,240],"ratio":81.36081560283688},{"color":[61,50,48],"ratio":13.292213671344498},{"color":[163,96,73],"ratio":1.180461244404205},{"color":[155,157,162],"ratio":2.8177028318495045},{"color":[181,150,111],"ratio":1.3488066495649111}]}