{"annotation":"","encodeName":"jobs","ext":"png","folders":["8ccc1398-312e-69c0-ff35-1c1c4df748fe"],"height":316,"id":"a2cc0172-2cae-a701-c162-ba66232b2737","isDeleted":false,"modificationTime":1504761794818,"name":"jobs","palettes":[{"$$hashKey":"object:4176","color":[41,33,105],"ratio":87.5979132723399},{"$$hashKey":"object:4177","color":[243,147,163],"ratio":11.31799097631282},{"$$hashKey":"object:4178","color":[44,211,214],"ratio":0.3462213309938589},{"$$hashKey":"object:4179","color":[116,89,140],"ratio":0.6344780047625015},{"$$hashKey":"object:4180","color":[64,127,190],"ratio":0.10339641559092619}],"size":43821,"tags":["LOGO"],"url":"https://www.behance.net/blingoucff0","width":404}