{"id":"304d185d-a912-c556-1da1-6a6467cf64c0","name":"Lix Logo Redesign on Behance","size":661748,"ext":"png","tags":[],"folders":[],"isDeleted":false,"url":"https://www.behance.net/gallery/59426147/Lix-Logo-Redesign","modificationTime":1513566656949,"width":3840,"height":4043,"palettes":[{"color":[251,251,251],"ratio":93.935852553542},{"color":[50,137,181],"ratio":3.2817648270181223},{"color":[204,70,168],"ratio":1.492740939044481},{"color":[231,190,49],"ratio":0.7259060955518946},{"color":[152,171,201],"ratio":0.5637355848434926}]}